setup.py
dot_snek.egg-info/PKG-INFO
dot_snek.egg-info/SOURCES.txt
dot_snek.egg-info/dependency_links.txt
dot_snek.egg-info/entry_points.txt
dot_snek.egg-info/top_level.txt
snek/__init__.py
snek/core.py
snek/main.py
snek/update.py