Metadata-Version: 1.0
Name: dot-snek
Version: 0.0.3
Summary: Dot files manager
Home-page: https://github.com/MaT1g3R/dot_snek
Author: MaT1g3R
Author-email: UNKNOWN
License: MIT
Platform: UNKNOWN
